{"commitInfo":{"timestamp":1705009219536,"operation":"DELETE","operationParameters":{"predicate":"[\"(LIMITE_CREDITO#2089 < 400000.0)\"]"},"readVersion":1,"isolationLevel":"Serializable","isBlindAppend":false,"operationMetrics":{"numRemovedFiles":"1","numRemovedBytes":"1541","numCopiedRows":"2","numAddedChangeFiles":"0","executionTimeMs":"1205","numDeletedRows":"1","scanTimeMs":"894","numAddedFiles":"1","numAddedBytes":"1517","rewriteTimeMs":"311"},"engineInfo":"Apache-Spark/3.4.2 Delta-Lake/2.4.0","txnId":"57bc0b12-b0af-43d6-8eb6-44f759c70181"}}
{"remove":{"path":"part-00000-4e56ee6c-994d-4bf6-99a1-dfe27a1c5f3c-c000.snappy.parquet","deletionTimestamp":1705009219518,"dataChange":true,"extendedFileMetadata":true,"partitionValues":{},"size":1541}}
{"add":{"path":"part-00000-84d4e68f-7336-48df-b068-42b7d88f0f6c-c000.snappy.parquet","partitionValues":{},"size":1517,"modificationTime":1705009219504,"dataChange":true,"stats":"{\"numRecords\":2,\"minValues\":{\"ID_CLIENTE\":\"ID002\",\"NOME_CLIENTE\":\"CLIENTE_Y\",\"UF\":\"DF\",\"STATUS\":\"ATIVO\",\"LIMITE_CREDITO\":400000.0},\"maxValues\":{\"ID_CLIENTE\":\"ID004\",\"NOME_CLIENTE\":\"CLIENTE_Z\",\"UF\":\"SC\",\"STATUS\":\"ATIVO\",\"LIMITE_CREDITO\":5000000.0},\"nullCount\":{\"ID_CLIENTE\":0,\"NOME_CLIENTE\":0,\"UF\":0,\"STATUS\":0,\"LIMITE_CREDITO\":0}}"}}
